{
	"start":	{
		"connected":	[{
				"socket":	5,
				"local_host":	"10.10.10.2",
				"local_port":	47402,
				"remote_host":	"10.10.10.4",
				"remote_port":	5201
			}],
		"version":	"iperf 3.9",
		"system_info":	"Linux zelda 5.10.0-18-amd64 #1 SMP Debian 5.10.140-1 (2022-09-02) x86_64",
		"timestamp":	{
			"time":	"Tue, 30 Jan 2024 12:56:45 GMT",
			"timesecs":	1706619405
		},
		"connecting_to":	{
			"host":	"10.10.10.4",
			"port":	5201
		},
		"cookie":	"n5egq4evptzji6x7mq5k4mpcekjo66aniyyp",
		"tcp_mss_default":	1448,
		"target_bitrate":	4000000000,
		"sock_bufsize":	0,
		"sndbuf_actual":	1000000,
		"rcvbuf_actual":	1000000,
		"test_start":	{
			"protocol":	"TCP",
			"num_streams":	1,
			"blksize":	131072,
			"omit":	0,
			"duration":	10,
			"bytes":	0,
			"blocks":	0,
			"reverse":	0,
			"tos":	0
		}
	},
	"intervals":	[{
			"streams":	[{
					"socket":	5,
					"start":	0,
					"end":	10.000079,
					"seconds":	10.000079154968262,
					"bytes":	1178468352,
					"bits_per_second":	942767219.12906921,
					"retransmits":	0,
					"snd_cwnd":	402544,
					"rtt":	2178,
					"rttvar":	117,
					"pmtu":	9000,
					"omitted":	false,
					"sender":	true
				}],
			"sum":	{
				"start":	0,
				"end":	10.000079,
				"seconds":	10.000079154968262,
				"bytes":	1178468352,
				"bits_per_second":	942767219.12906921,
				"retransmits":	0,
				"omitted":	false,
				"sender":	true
			}
		}],
	"end":	{
		"streams":	[{
				"sender":	{
					"socket":	5,
					"start":	0,
					"end":	10.000079,
					"seconds":	10.000079,
					"bytes":	1178468352,
					"bits_per_second":	942767233.73885345,
					"retransmits":	0,
					"max_snd_cwnd":	402544,
					"max_rtt":	2178,
					"min_rtt":	2178,
					"mean_rtt":	2178,
					"sender":	true
				},
				"receiver":	{
					"socket":	5,
					"start":	0,
					"end":	10.043544054031372,
					"seconds":	10.000079,
					"bytes":	1177032168,
					"bits_per_second":	937543290.82874024,
					"sender":	true
				}
			}],
		"sum_sent":	{
			"start":	0,
			"end":	10.000079,
			"seconds":	10.000079,
			"bytes":	1178468352,
			"bits_per_second":	942767233.73885345,
			"retransmits":	0,
			"sender":	true
		},
		"sum_received":	{
			"start":	0,
			"end":	10.043544054031372,
			"seconds":	10.043544054031372,
			"bytes":	1177032168,
			"bits_per_second":	937543290.82874024,
			"sender":	true
		},
		"cpu_utilization_percent":	{
			"host_total":	17.17799645853751,
			"host_user":	0.26127753173824109,
			"host_system":	16.9167288401978,
			"remote_total":	27.365273375915137,
			"remote_user":	2.3248221072503763,
			"remote_system":	25.040451268664764
		},
		"sender_tcp_congestion":	"cubic",
		"receiver_tcp_congestion":	"cubic"
	}
}
