{
	"start":	{
		"connected":	[{
				"socket":	5,
				"local_host":	"10.10.10.2",
				"local_port":	58132,
				"remote_host":	"10.10.10.4",
				"remote_port":	5201
			}],
		"version":	"iperf 3.9",
		"system_info":	"Linux zelda 5.10.0-18-amd64 #1 SMP Debian 5.10.140-1 (2022-09-02) x86_64",
		"timestamp":	{
			"time":	"Mon, 29 Jan 2024 19:37:44 GMT",
			"timesecs":	1706557064
		},
		"connecting_to":	{
			"host":	"10.10.10.4",
			"port":	5201
		},
		"cookie":	"6nrnfxxnqf6nid3fzq52zvbrhtyutps23dod",
		"tcp_mss_default":	1448,
		"target_bitrate":	6000000000,
		"sock_bufsize":	0,
		"sndbuf_actual":	1000000,
		"rcvbuf_actual":	1000000,
		"test_start":	{
			"protocol":	"TCP",
			"num_streams":	1,
			"blksize":	131072,
			"omit":	0,
			"duration":	90,
			"bytes":	0,
			"blocks":	0,
			"reverse":	0,
			"tos":	0
		}
	},
	"intervals":	[{
			"streams":	[{
					"socket":	5,
					"start":	0,
					"end":	60.000063,
					"seconds":	60.000064849853516,
					"bytes":	7061635072,
					"bits_per_second":	941550325.27665544,
					"retransmits":	120,
					"snd_cwnd":	556032,
					"rtt":	2206,
					"rttvar":	96,
					"pmtu":	9000,
					"omitted":	false,
					"sender":	true
				}],
			"sum":	{
				"start":	0,
				"end":	60.000063,
				"seconds":	60.000064849853516,
				"bytes":	7061635072,
				"bits_per_second":	941550325.27665544,
				"retransmits":	120,
				"omitted":	false,
				"sender":	true
			}
		}, {
			"streams":	[{
					"socket":	5,
					"start":	60.000063,
					"end":	90.000071,
					"seconds":	30.000007629394531,
					"bytes":	3530424320,
					"bits_per_second":	941446245.911172,
					"retransmits":	5,
					"snd_cwnd":	489424,
					"rtt":	2244,
					"rttvar":	152,
					"pmtu":	9000,
					"omitted":	false,
					"sender":	true
				}],
			"sum":	{
				"start":	60.000063,
				"end":	90.000071,
				"seconds":	30.000007629394531,
				"bytes":	3530424320,
				"bits_per_second":	941446245.911172,
				"retransmits":	5,
				"omitted":	false,
				"sender":	true
			}
		}],
	"end":	{
		"streams":	[{
				"sender":	{
					"socket":	5,
					"start":	0,
					"end":	90.000071,
					"seconds":	90.000071,
					"bytes":	10592059392,
					"bits_per_second":	941515647.64876676,
					"retransmits":	125,
					"max_snd_cwnd":	556032,
					"max_rtt":	2244,
					"min_rtt":	2206,
					"mean_rtt":	2225,
					"sender":	true
				},
				"receiver":	{
					"socket":	5,
					"start":	0,
					"end":	90.043881893157959,
					"seconds":	90.000071,
					"bytes":	10589523040,
					"bits_per_second":	940832209.12799418,
					"sender":	true
				}
			}],
		"sum_sent":	{
			"start":	0,
			"end":	90.000071,
			"seconds":	90.000071,
			"bytes":	10592059392,
			"bits_per_second":	941515647.64876676,
			"retransmits":	125,
			"sender":	true
		},
		"sum_received":	{
			"start":	0,
			"end":	90.043881893157959,
			"seconds":	90.043881893157959,
			"bytes":	10589523040,
			"bits_per_second":	940832209.12799418,
			"sender":	true
		},
		"cpu_utilization_percent":	{
			"host_total":	8.53485289808097,
			"host_user":	0.28620825156071,
			"host_system":	8.24864464652026,
			"remote_total":	23.426224970071587,
			"remote_user":	2.1707699028176473,
			"remote_system":	21.255453957643414
		},
		"sender_tcp_congestion":	"cubic",
		"receiver_tcp_congestion":	"cubic"
	}
}
