{
	"start":	{
		"connected":	[{
				"socket":	5,
				"local_host":	"10.10.10.2",
				"local_port":	49410,
				"remote_host":	"10.10.10.4",
				"remote_port":	5201
			}],
		"version":	"iperf 3.9",
		"system_info":	"Linux zelda 5.10.0-18-amd64 #1 SMP Debian 5.10.140-1 (2022-09-02) x86_64",
		"timestamp":	{
			"time":	"Mon, 29 Jan 2024 12:05:08 GMT",
			"timesecs":	1706529908
		},
		"connecting_to":	{
			"host":	"10.10.10.4",
			"port":	5201
		},
		"cookie":	"5zlow53ijkgswxlhe5z7e54wfw6cuvgu46ks",
		"tcp_mss_default":	1448,
		"target_bitrate":	1000000000,
		"sock_bufsize":	0,
		"sndbuf_actual":	1000000,
		"rcvbuf_actual":	1000000,
		"test_start":	{
			"protocol":	"TCP",
			"num_streams":	1,
			"blksize":	131072,
			"omit":	0,
			"duration":	90,
			"bytes":	0,
			"blocks":	0,
			"reverse":	0,
			"tos":	0
		}
	},
	"intervals":	[{
			"streams":	[{
					"socket":	5,
					"start":	0,
					"end":	60.000072,
					"seconds":	60.000072479248047,
					"bytes":	7062290432,
					"bits_per_second":	941637586.780263,
					"retransmits":	21,
					"snd_cwnd":	364896,
					"rtt":	1718,
					"rttvar":	129,
					"pmtu":	9000,
					"omitted":	false,
					"sender":	true
				}],
			"sum":	{
				"start":	0,
				"end":	60.000072,
				"seconds":	60.000072479248047,
				"bytes":	7062290432,
				"bits_per_second":	941637586.780263,
				"retransmits":	21,
				"omitted":	false,
				"sender":	true
			}
		}, {
			"streams":	[{
					"socket":	5,
					"start":	60.000072,
					"end":	90.000092,
					"seconds":	30.000019073486328,
					"bytes":	3529768960,
					"bits_per_second":	941271124.22260273,
					"retransmits":	51,
					"snd_cwnd":	357656,
					"rtt":	2222,
					"rttvar":	99,
					"pmtu":	9000,
					"omitted":	false,
					"sender":	true
				}],
			"sum":	{
				"start":	60.000072,
				"end":	90.000092,
				"seconds":	30.000019073486328,
				"bytes":	3529768960,
				"bits_per_second":	941271124.22260273,
				"retransmits":	51,
				"omitted":	false,
				"sender":	true
			}
		}],
	"end":	{
		"streams":	[{
				"sender":	{
					"socket":	5,
					"start":	0,
					"end":	90.000092,
					"seconds":	90.000092,
					"bytes":	10592059392,
					"bits_per_second":	941515427.962007,
					"retransmits":	72,
					"max_snd_cwnd":	364896,
					"max_rtt":	2222,
					"min_rtt":	1718,
					"mean_rtt":	1970,
					"sender":	true
				},
				"receiver":	{
					"socket":	5,
					"start":	0,
					"end":	90.040666103363037,
					"seconds":	90.000092,
					"bytes":	10590273328,
					"bits_per_second":	940932472.96440876,
					"sender":	true
				}
			}],
		"sum_sent":	{
			"start":	0,
			"end":	90.000092,
			"seconds":	90.000092,
			"bytes":	10592059392,
			"bits_per_second":	941515427.962007,
			"retransmits":	72,
			"sender":	true
		},
		"sum_received":	{
			"start":	0,
			"end":	90.040666103363037,
			"seconds":	90.040666103363037,
			"bytes":	10590273328,
			"bits_per_second":	940932472.96440876,
			"sender":	true
		},
		"cpu_utilization_percent":	{
			"host_total":	8.45989004163194,
			"host_user":	0.29836483137668046,
			"host_system":	8.16153853130318,
			"remote_total":	26.835467675275236,
			"remote_user":	2.6002449023525385,
			"remote_system":	24.23522166326093
		},
		"sender_tcp_congestion":	"cubic",
		"receiver_tcp_congestion":	"cubic"
	}
}
