{
	"start":	{
		"connected":	[{
				"socket":	5,
				"local_host":	"10.10.10.2",
				"local_port":	36456,
				"remote_host":	"10.10.10.4",
				"remote_port":	5201
			}],
		"version":	"iperf 3.9",
		"system_info":	"Linux zelda 5.10.0-18-amd64 #1 SMP Debian 5.10.140-1 (2022-09-02) x86_64",
		"timestamp":	{
			"time":	"Wed, 31 Jan 2024 11:58:52 GMT",
			"timesecs":	1706702332
		},
		"connecting_to":	{
			"host":	"10.10.10.4",
			"port":	5201
		},
		"cookie":	"dosqaqobuat74kwrwl6tydkqrvuzbpm5funs",
		"tcp_mss_default":	1448,
		"target_bitrate":	8000000000,
		"sock_bufsize":	0,
		"sndbuf_actual":	1000000,
		"rcvbuf_actual":	1000000,
		"test_start":	{
			"protocol":	"TCP",
			"num_streams":	1,
			"blksize":	131072,
			"omit":	0,
			"duration":	100,
			"bytes":	0,
			"blocks":	0,
			"reverse":	0,
			"tos":	0
		}
	},
	"intervals":	[{
			"streams":	[{
					"socket":	5,
					"start":	0,
					"end":	60.000089,
					"seconds":	60.0000877380371,
					"bytes":	7062945792,
					"bits_per_second":	941724728.515347,
					"retransmits":	0,
					"snd_cwnd":	492320,
					"rtt":	2412,
					"rttvar":	117,
					"pmtu":	9000,
					"omitted":	false,
					"sender":	true
				}],
			"sum":	{
				"start":	0,
				"end":	60.000089,
				"seconds":	60.0000877380371,
				"bytes":	7062945792,
				"bits_per_second":	941724728.515347,
				"retransmits":	0,
				"omitted":	false,
				"sender":	true
			}
		}, {
			"streams":	[{
					"socket":	5,
					"start":	60.000089,
					"end":	100.000079,
					"seconds":	39.9999885559082,
					"bytes":	4707450880,
					"bits_per_second":	941490445.362577,
					"retransmits":	0,
					"snd_cwnd":	492320,
					"rtt":	2224,
					"rttvar":	152,
					"pmtu":	9000,
					"omitted":	false,
					"sender":	true
				}],
			"sum":	{
				"start":	60.000089,
				"end":	100.000079,
				"seconds":	39.9999885559082,
				"bytes":	4707450880,
				"bits_per_second":	941490445.362577,
				"retransmits":	0,
				"omitted":	false,
				"sender":	true
			}
		}],
	"end":	{
		"streams":	[{
				"sender":	{
					"socket":	5,
					"start":	0,
					"end":	100.000079,
					"seconds":	100.000079,
					"bytes":	11770396672,
					"bits_per_second":	941630989.871518,
					"retransmits":	0,
					"max_snd_cwnd":	492320,
					"max_rtt":	2412,
					"min_rtt":	2224,
					"mean_rtt":	2318,
					"sender":	true
				},
				"receiver":	{
					"socket":	5,
					"start":	0,
					"end":	100.04381203651428,
					"seconds":	100.000079,
					"bytes":	11768590344,
					"bits_per_second":	941074923.43091965,
					"sender":	true
				}
			}],
		"sum_sent":	{
			"start":	0,
			"end":	100.000079,
			"seconds":	100.000079,
			"bytes":	11770396672,
			"bits_per_second":	941630989.871518,
			"retransmits":	0,
			"sender":	true
		},
		"sum_received":	{
			"start":	0,
			"end":	100.04381203651428,
			"seconds":	100.04381203651428,
			"bytes":	11768590344,
			"bits_per_second":	941074923.43091965,
			"sender":	true
		},
		"cpu_utilization_percent":	{
			"host_total":	18.321528563741609,
			"host_user":	0.67673671554015336,
			"host_system":	17.644790849041968,
			"remote_total":	26.4119132612614,
			"remote_user":	2.6316661602972222,
			"remote_system":	23.780247100964182
		},
		"sender_tcp_congestion":	"cubic",
		"receiver_tcp_congestion":	"cubic"
	}
}
