{
	"start":	{
		"connected":	[{
				"socket":	5,
				"local_host":	"10.10.10.2",
				"local_port":	41128,
				"remote_host":	"10.10.10.4",
				"remote_port":	5201
			}],
		"version":	"iperf 3.9",
		"system_info":	"Linux zelda 5.10.0-18-amd64 #1 SMP Debian 5.10.140-1 (2022-09-02) x86_64",
		"timestamp":	{
			"time":	"Tue, 30 Jan 2024 00:15:18 GMT",
			"timesecs":	1706573718
		},
		"connecting_to":	{
			"host":	"10.10.10.4",
			"port":	5201
		},
		"cookie":	"5ekdosgbc6zvaqb7gtykcfcttjvya65sjkfg",
		"tcp_mss_default":	1448,
		"target_bitrate":	9000000000,
		"sock_bufsize":	0,
		"sndbuf_actual":	1000000,
		"rcvbuf_actual":	1000000,
		"test_start":	{
			"protocol":	"TCP",
			"num_streams":	1,
			"blksize":	131072,
			"omit":	0,
			"duration":	90,
			"bytes":	0,
			"blocks":	0,
			"reverse":	0,
			"tos":	0
		}
	},
	"intervals":	[{
			"streams":	[{
					"socket":	5,
					"start":	0,
					"end":	60.00007,
					"seconds":	60.000068664550781,
					"bytes":	7063076864,
					"bits_per_second":	941742504.1279,
					"retransmits":	0,
					"snd_cwnd":	516936,
					"rtt":	2722,
					"rttvar":	100,
					"pmtu":	9000,
					"omitted":	false,
					"sender":	true
				}],
			"sum":	{
				"start":	0,
				"end":	60.00007,
				"seconds":	60.000068664550781,
				"bytes":	7063076864,
				"bits_per_second":	941742504.1279,
				"retransmits":	0,
				"omitted":	false,
				"sender":	true
			}
		}, {
			"streams":	[{
					"socket":	5,
					"start":	60.00007,
					"end":	90.000077,
					"seconds":	30.000007629394531,
					"bytes":	3530555392,
					"bits_per_second":	941481198.43561649,
					"retransmits":	0,
					"snd_cwnd":	516936,
					"rtt":	2257,
					"rttvar":	107,
					"pmtu":	9000,
					"omitted":	false,
					"sender":	true
				}],
			"sum":	{
				"start":	60.00007,
				"end":	90.000077,
				"seconds":	30.000007629394531,
				"bytes":	3530555392,
				"bits_per_second":	941481198.43561649,
				"retransmits":	0,
				"omitted":	false,
				"sender":	true
			}
		}],
	"end":	{
		"streams":	[{
				"sender":	{
					"socket":	5,
					"start":	0,
					"end":	90.000077,
					"seconds":	90.000077,
					"bytes":	10593632256,
					"bits_per_second":	941655394.8948288,
					"retransmits":	0,
					"max_snd_cwnd":	516936,
					"max_rtt":	2722,
					"min_rtt":	2257,
					"mean_rtt":	2489,
					"sender":	true
				},
				"receiver":	{
					"socket":	5,
					"start":	0,
					"end":	90.0452139377594,
					"seconds":	90.000077,
					"bytes":	10591870248,
					"bits_per_second":	941026827.284458,
					"sender":	true
				}
			}],
		"sum_sent":	{
			"start":	0,
			"end":	90.000077,
			"seconds":	90.000077,
			"bytes":	10593632256,
			"bits_per_second":	941655394.8948288,
			"retransmits":	0,
			"sender":	true
		},
		"sum_received":	{
			"start":	0,
			"end":	90.0452139377594,
			"seconds":	90.0452139377594,
			"bytes":	10591870248,
			"bits_per_second":	941026827.284458,
			"sender":	true
		},
		"cpu_utilization_percent":	{
			"host_total":	8.5471236376029,
			"host_user":	0.31575393448923111,
			"host_system":	8.23136970311367,
			"remote_total":	23.736582616332257,
			"remote_user":	2.5509974585735282,
			"remote_system":	21.185584048207769
		},
		"sender_tcp_congestion":	"cubic",
		"receiver_tcp_congestion":	"cubic"
	}
}
