{
	"start":	{
		"connected":	[{
				"socket":	5,
				"local_host":	"10.10.10.2",
				"local_port":	43806,
				"remote_host":	"10.10.10.4",
				"remote_port":	5201
			}],
		"version":	"iperf 3.9",
		"system_info":	"Linux zelda 5.10.0-18-amd64 #1 SMP Debian 5.10.140-1 (2022-09-02) x86_64",
		"timestamp":	{
			"time":	"Wed, 31 Jan 2024 10:56:11 GMT",
			"timesecs":	1706698571
		},
		"connecting_to":	{
			"host":	"10.10.10.4",
			"port":	5201
		},
		"cookie":	"n2vwctkf3epu737ifhavtctedivq4orimx4p",
		"tcp_mss_default":	1448,
		"target_bitrate":	8000000000,
		"sock_bufsize":	0,
		"sndbuf_actual":	1000000,
		"rcvbuf_actual":	1000000,
		"test_start":	{
			"protocol":	"TCP",
			"num_streams":	1,
			"blksize":	131072,
			"omit":	0,
			"duration":	50,
			"bytes":	0,
			"blocks":	0,
			"reverse":	0,
			"tos":	0
		}
	},
	"intervals":	[{
			"streams":	[{
					"socket":	5,
					"start":	0,
					"end":	50.00007,
					"seconds":	50.000068664550781,
					"bytes":	5886967808,
					"bits_per_second":	941913555.75857639,
					"retransmits":	0,
					"snd_cwnd":	728344,
					"rtt":	2718,
					"rttvar":	92,
					"pmtu":	9000,
					"omitted":	false,
					"sender":	true
				}],
			"sum":	{
				"start":	0,
				"end":	50.00007,
				"seconds":	50.000068664550781,
				"bytes":	5886967808,
				"bits_per_second":	941913555.75857639,
				"retransmits":	0,
				"omitted":	false,
				"sender":	true
			}
		}],
	"end":	{
		"streams":	[{
				"sender":	{
					"socket":	5,
					"start":	0,
					"end":	50.00007,
					"seconds":	50.00007,
					"bytes":	5886967808,
					"bits_per_second":	941913530.601057,
					"retransmits":	0,
					"max_snd_cwnd":	728344,
					"max_rtt":	2718,
					"min_rtt":	2718,
					"mean_rtt":	2718,
					"sender":	true
				},
				"receiver":	{
					"socket":	5,
					"start":	0,
					"end":	50.04456090927124,
					"seconds":	50.00007,
					"bytes":	5884516368,
					"bits_per_second":	940684263.95721841,
					"sender":	true
				}
			}],
		"sum_sent":	{
			"start":	0,
			"end":	50.00007,
			"seconds":	50.00007,
			"bytes":	5886967808,
			"bits_per_second":	941913530.601057,
			"retransmits":	0,
			"sender":	true
		},
		"sum_received":	{
			"start":	0,
			"end":	50.04456090927124,
			"seconds":	50.04456090927124,
			"bytes":	5884516368,
			"bits_per_second":	940684263.95721841,
			"sender":	true
		},
		"cpu_utilization_percent":	{
			"host_total":	18.642789426494925,
			"host_user":	0.74939260211478242,
			"host_system":	17.893394827772855,
			"remote_total":	26.278048801803028,
			"remote_user":	2.3770119785278818,
			"remote_system":	23.90103482801441
		},
		"sender_tcp_congestion":	"cubic",
		"receiver_tcp_congestion":	"cubic"
	}
}
